CHANGELOG.md
wikitools3/LICENSE.md
wikitools3/__init__.py
wikitools3/api.py
wikitools3/category.py
wikitools3/page.py
wikitools3/pagelist.py
wikitools3/user.py
wikitools3/wiki.py
wikitools3/wikifile.py
wikitools3-3.0.1.dist-info/WHEEL
wikitools3-3.0.1.dist-info/METADATA
wikitools3-3.0.1.dist-info/RECORD
