Metadata-Version: 2.1
Name: wikitools3
Version: 3.0.1
Summary: Python package for interacting with a MediaWiki wiki. It is used by WikiTeam for archiving MediaWiki wikis.
Home-page: https://github.com/elsiehupp/wikitools3
License: GPL-3.0-or-later
Keywords: wikipedia,mediawiki,archive,scrape,archiveteam
Author: Alex Zaddach
Author-email: mrzmanwiki@gmail.com
Maintainer: Elsie Hupp
Maintainer-email: wikitools3@elsiehupp.com
Requires-Python: >=3.8,<4.0
Classifier: Development Status :: 4 - Beta
Classifier: Intended Audience :: Developers
Classifier: License :: OSI Approved :: GNU General Public License v3 or later (GPLv3+)
Classifier: Natural Language :: English
Classifier: Operating System :: OS Independent
Classifier: Programming Language :: Python
Classifier: Programming Language :: Python :: 3
Classifier: Programming Language :: Python :: 3.8
Classifier: Programming Language :: Python :: 3.9
Classifier: Topic :: Internet :: WWW/HTTP :: Dynamic Content :: Wiki
Classifier: Topic :: Software Development :: Libraries :: Python Modules
Requires-Dist: poster3 (>=0.8.1,<0.9.0)
Project-URL: Repository, https://github.com/elsiehupp/wikitools3
